{
  "0": {
    "rank": 178,
    "attributes": {
      "Background": "Yellow",
      "Body": "Black",
      "Eyes": "Sunglasses",
      "Hats": "Thought Bubble",
      "Legs": "Normal",
      "Mouth": "Shocked"
    }
  },
  "1": {
    "rank": 5,
    "attributes": {
      "Background": "Purple",
      "Body": "Lemon",
      "Eyes": "X",
      "Hats": "Bow",
      "Legs": "Normal",
      "Mouth": "Joy"
    }
  },
  "2": {
    "rank": 75,
    "attributes": {
      "Background": "Green",
      "Body": "Pink Lemon",
      "Eyes": "Stars",
      "Hats": "Bow",
      "Legs": "Normal",
      "Mouth": "Joy"
    }
  },
  "3": {
    "rank": 90,
    "attributes": {
      "Background": "Green",
      "Body": "Lime",
      "Eyes": "Sunglasses",
      "Hats": "Chocolate Ice Cream",
      "Legs": "Normal",
      "Mouth": "Shocked"
    }
  },
  "4": {
    "rank": 1,
    "attributes": {
      "Background": "Solana",
      "Body": "Red",
      "Eyes": "VR",
      "Hats": "Drink",
      "Legs": "Normal",
      "Mouth": "Joy"
    }
  },
  "5": {
    "rank": 162,
    "attributes": {
      "Background": "Yellow",
      "Body": "Pink Lemon",
      "Eyes": "Glasses",
      "Hats": "Strawberry Ice Cream",
      "Legs": "Normal",
      "Mouth": "Joy"
    }
  },
  "6": {
    "rank": 109,
    "attributes": {
      "Background": "Sky",
      "Body": "Black",
      "Eyes": "ETH",
      "Hats": "Fire",
      "Legs": "Normal",
      "Mouth": "Pumpkin"
    }
  },
  "7": {
    "rank": 332,
    "attributes": {
      "Background": "Yellow",
      "Body": "Pink Lemon",
      "Eyes": "Block",
      "Hats": "Nothing",
      "Legs": "Normal",
      "Mouth": "Joy"
    }
  },
  "8": {
    "rank": 106,
    "attributes": {
      "Background": "Sky",
      "Body": "Tatted",
      "Eyes": "Cute",
      "Hats": "Bow",
      "Legs": "Normal",
      "Mouth": "Shocked"
    }
  },
  "9": {
    "rank": 47,
    "attributes": {
      "Background": "Solana",
      "Body": "Lime",
      "Eyes": "Hypnotized",
      "Hats": "Flower",
      "Legs": "Normal",
      "Mouth": "Pumpkin"
    }
  },
  "10": {
    "rank": 279,
    "attributes": {
      "Background": "Green",
      "Body": "Lime",
      "Eyes": "Stare",
      "Hats": "Signal",
      "Legs": "Normal",
      "Mouth": "Not Amused"
    }
  },
  "11": {
    "rank": 82,
    "attributes": {
      "Background": "Yellow",
      "Body": "Black",
      "Eyes": "Heart",
      "Hats": "Chocolate Ice Cream",
      "Legs": "Normal",
      "Mouth": "Not Amused"
    }
  },
  "12": {
    "rank": 36,
    "attributes": {
      "Background": "Sky",
      "Body": "Pink Lemon",
      "Eyes": "VR",
      "Hats": "Fire",
      "Legs": "Normal",
      "Mouth": "Joy"
    }
  },
  "13": {
    "rank": 239,
    "attributes": {
      "Background": "Rainbow",
      "Body": "Tatted",
      "Eyes": "Glasses",
      "Hats": "Signal",
      "Legs": "Normal",
      "Mouth": "Bubblegum"
    }
  },
  "14": {
    "rank": 46,
    "attributes": {
      "Background": "Purple",
      "Body": "Black",
      "Eyes": "VR",
      "Hats": "Strawberry Ice Cream",
      "Legs": "Normal",
      "Mouth": "Shocked"
    }
  },
  "15": {
    "rank": 270,
    "attributes": {
      "Background": "Purple",
      "Body": "Pink Lemon",
      "Eyes": "Cute",
      "Hats": "Cloudy",
      "Legs": "Normal",
      "Mouth": "Joy"
    }
  },
  "16": {
    "rank": 236,
    "attributes": {
      "Background": "Rainbow",
      "Body": "Lime",
      "Eyes": "Heart",
      "Hats": "Traffic Cone",
      "Legs": "Normal",
      "Mouth": "Shocked"
    }
  },
  "17": {
    "rank": 87,
    "attributes": {
      "Background": "Yellow",
      "Body": "Pink Lemon",
      "Eyes": "Cyborg",
      "Hats": "Halo",
      "Legs": "Normal",
      "Mouth": "Happy"
    }
  },
  "18": {
    "rank": 104,
    "attributes": {
      "Background": "Rainbow",
      "Body": "Red",
      "Eyes": "Sunglasses",
      "Hats": "Thought Bubble",
      "Legs": "Normal",
      "Mouth": "Pumpkin"
    }
  },
  "19": {
    "rank": 79,
    "attributes": {
      "Background": "Sky",
      "Body": "Red",
      "Eyes": "SOL",
      "Hats": "Strawberry Ice Cream",
      "Legs": "Normal",
      "Mouth": "Shocked"
    }
  },
  "20": {
    "rank": 283,
    "attributes": {
      "Background": "Green",
      "Body": "Pink Lemon",
      "Eyes": "SOL",
      "Hats": "Signal",
      "Legs": "Normal",
      "Mouth": "Shocked"
    }
  },
  "21": {
    "rank": 119,
    "attributes": {
      "Background": "Green",
      "Body": "Lime",
      "Eyes": "Stars",
      "Hats": "Demon Horns",
      "Legs": "Normal",
      "Mouth": "Not Amused"
    }
  },
  "22": {
    "rank": 133,
    "attributes": {
      "Background": "Sky",
      "Body": "Tatted",
      "Eyes": "Cute",
      "Hats": "Signal",
      "Legs": "Normal",
      "Mouth": "Joy"
    }
  },
  "23": {
    "rank": 93,
    "attributes": {
      "Background": "Sky",
      "Body": "Lime",
      "Eyes": "Hypnotized",
      "Hats": "Strawberry Ice Cream",
      "Legs": "Normal",
      "Mouth": "Bubblegum"
    }
  },
  "24": {
    "rank": 203,
    "attributes": {
      "Background": "Rainbow",
      "Body": "Lemon",
      "Eyes": "Happy",
      "Hats": "Horns",
      "Legs": "Normal",
      "Mouth": "Not Amused"
    }
  },
  "25": {
    "rank": 261,
    "attributes": {
      "Background": "Green",
      "Body": "Black",
      "Eyes": "Block",
      "Hats": "Demon Horns",
      "Legs": "Normal",
      "Mouth": "Pumpkin"
    }
  },
  "26": {
    "rank": 76,
    "attributes": {
      "Background": "Green",
      "Body": "Red",
      "Eyes": "ETH",
      "Hats": "Balloon-",
      "Legs": "Normal",
      "Mouth": "Joy"
    }
  },
  "27": {
    "rank": 80,
    "attributes": {
      "Background": "Yellow",
      "Body": "Tatted",
      "Eyes": "X",
      "Hats": "Thought Bubble",
      "Legs": "Normal",
      "Mouth": "Pumpkin"
    }
  },
  "28": {
    "rank": 233,
    "attributes": {
      "Background": "Yellow",
      "Body": "Lemon",
      "Eyes": "Cute",
      "Hats": "Horns",
      "Legs": "Normal",
      "Mouth": "Shocked"
    }
  },
  "29": {
    "rank": 156,
    "attributes": {
      "Background": "Yellow",
      "Body": "Red",
      "Eyes": "Stars",
      "Hats": "Traffic Cone",
      "Legs": "Normal",
      "Mouth": "Shocked"
    }
  },
  "30": {
    "rank": 160,
    "attributes": {
      "Background": "Yellow",
      "Body": "Black",
      "Eyes": "ETH",
      "Hats": "Bow",
      "Legs": "Normal",
      "Mouth": "Shocked"
    }
  },
  "31": {
    "rank": 316,
    "attributes": {
      "Background": "Green",
      "Body": "Red",
      "Eyes": "Block",
      "Hats": "Cloudy",
      "Legs": "Normal",
      "Mouth": "Shocked"
    }
  },
  "32": {
    "rank": 192,
    "attributes": {
      "Background": "Rainbow",
      "Body": "Pink Lemon",
      "Eyes": "Glasses",
      "Hats": "Fire",
      "Legs": "Normal",
      "Mouth": "Not Amused"
    }
  },
  "33": {
    "rank": 19,
    "attributes": {
      "Background": "Green",
      "Body": "Pink Lemon",
      "Eyes": "X",
      "Hats": "Strawberry Ice Cream",
      "Legs": "Normal",
      "Mouth": "Bubblegum"
    }
  },
  "34": {
    "rank": 138,
    "attributes": {
      "Background": "Purple",
      "Body": "Lime",
      "Eyes": "Stare",
      "Hats": "Pink Bow",
      "Legs": "Normal",
      "Mouth": "Not Amused"
    }
  },
  "35": {
    "rank": 320,
    "attributes": {
      "Background": "Green",
      "Body": "Lime",
      "Eyes": "Cute",
      "Hats": "Nothing",
      "Legs": "Normal",
      "Mouth": "Bubblegum"
    }
  },
  "36": {
    "rank": 43,
    "attributes": {
      "Background": "Sky",
      "Body": "Black",
      "Eyes": "SOL",
      "Hats": "Balloon-",
      "Legs": "Normal",
      "Mouth": "Bubblegum"
    }
  },
  "37": {
    "rank": 159,
    "attributes": {
      "Background": "Solana",
      "Body": "Black",
      "Eyes": "Heart",
      "Hats": "Fire",
      "Legs": "Normal",
      "Mouth": "Pumpkin"
    }
  },
  "38": {
    "rank": 297,
    "attributes": {
      "Background": "Rainbow",
      "Body": "Lemon",
      "Eyes": "Stare",
      "Hats": "Cloudy",
      "Legs": "Normal",
      "Mouth": "Shocked"
    }
  },
  "39": {
    "rank": 244,
    "attributes": {
      "Background": "Yellow",
      "Body": "Pink Lemon",
      "Eyes": "Pumpkin",
      "Hats": "Fire",
      "Legs": "Normal",
      "Mouth": "Joy"
    }
  },
  "40": {
    "rank": 274,
    "attributes": {
      "Background": "Yellow",
      "Body": "Tatted",
      "Eyes": "Heart",
      "Hats": "Demon Horns",
      "Legs": "Normal",
      "Mouth": "Pumpkin"
    }
  },
  "41": {
    "rank": 23,
    "attributes": {
      "Background": "Solana",
      "Body": "Red",
      "Eyes": "Hypnotized",
      "Hats": "Chocolate Ice Cream",
      "Legs": "Normal",
      "Mouth": "Pumpkin"
    }
  },
  "42": {
    "rank": 9,
    "attributes": {
      "Background": "Sky",
      "Body": "Lemon",
      "Eyes": "Pumpkin",
      "Hats": "Balloon-",
      "Legs": "Normal",
      "Mouth": "Not Amused"
    }
  },
  "43": {
    "rank": 85,
    "attributes": {
      "Background": "Solana",
      "Body": "Red",
      "Eyes": "Stare",
      "Hats": "Balloon-",
      "Legs": "Normal",
      "Mouth": "Not Amused"
    }
  },
  "44": {
    "rank": 148,
    "attributes": {
      "Background": "Solana",
      "Body": "Pink Lemon",
      "Eyes": "Block",
      "Hats": "Pink Bow",
      "Legs": "Normal",
      "Mouth": "Pumpkin"
    }
  },
  "45": {
    "rank": 134,
    "attributes": {
      "Background": "Green",
      "Body": "Red",
      "Eyes": "Pumpkin",
      "Hats": "Demon Horns",
      "Legs": "Normal",
      "Mouth": "Bubblegum"
    }
  },
  "46": {
    "rank": 266,
    "attributes": {
      "Background": "Rainbow",
      "Body": "Lemon",
      "Eyes": "Block",
      "Hats": "Halo",
      "Legs": "Normal",
      "Mouth": "Not Amused"
    }
  },
  "47": {
    "rank": 56,
    "attributes": {
      "Background": "Solana",
      "Body": "Pink Lemon",
      "Eyes": "Sunglasses",
      "Hats": "Horns",
      "Legs": "Normal",
      "Mouth": "Not Amused"
    }
  },
  "48": {
    "rank": 103,
    "attributes": {
      "Background": "Rainbow",
      "Body": "Tatted",
      "Eyes": "Cute",
      "Hats": "Drink",
      "Legs": "Normal",
      "Mouth": "Bubblegum"
    }
  },
  "49": {
    "rank": 30,
    "attributes": {
      "Background": "Green",
      "Body": "Pink Lemon",
      "Eyes": "Stars",
      "Hats": "Drink",
      "Legs": "Normal",
      "Mouth": "Pumpkin"
    }
  },
  "50": {
    "rank": 146,
    "attributes": {
      "Background": "Yellow",
      "Body": "Lemon",
      "Eyes": "Heart",
      "Hats": "Balloon-",
      "Legs": "Normal",
      "Mouth": "Pumpkin"
    }
  },
  "51": {
    "rank": 48,
    "attributes": {
      "Background": "Sky",
      "Body": "Red",
      "Eyes": "Hypnotized",
      "Hats": "Thought Bubble",
      "Legs": "Normal",
      "Mouth": "Not Amused"
    }
  },
  "52": {
    "rank": 245,
    "attributes": {
      "Background": "Yellow",
      "Body": "Lemon",
      "Eyes": "Glasses",
      "Hats": "Fire",
      "Legs": "Normal",
      "Mouth": "Shocked"
    }
  },
  "53": {
    "rank": 240,
    "attributes": {
      "Background": "Purple",
      "Body": "Lemon",
      "Eyes": "Block",
      "Hats": "Demon Horns",
      "Legs": "Normal",
      "Mouth": "Not Amused"
    }
  },
  "54": {
    "rank": 55,
    "attributes": {
      "Background": "Yellow",
      "Body": "Black",
      "Eyes": "Sunglasses",
      "Hats": "Bow",
      "Legs": "Normal",
      "Mouth": "Pumpkin"
    }
  },
  "55": {
    "rank": 293,
    "attributes": {
      "Background": "Green",
      "Body": "Red",
      "Eyes": "Happy",
      "Hats": "Halo",
      "Legs": "Normal",
      "Mouth": "Shocked"
    }
  },
  "56": {
    "rank": 126,
    "attributes": {
      "Background": "Solana",
      "Body": "Lemon",
      "Eyes": "ETH",
      "Hats": "Traffic Cone",
      "Legs": "Normal",
      "Mouth": "Shocked"
    }
  },
  "57": {
    "rank": 187,
    "attributes": {
      "Background": "Purple",
      "Body": "Tatted",
      "Eyes": "Hypnotized",
      "Hats": "Balloon-",
      "Legs": "Normal",
      "Mouth": "Bubblegum"
    }
  },
  "58": {
    "rank": 37,
    "attributes": {
      "Background": "Solana",
      "Body": "Red",
      "Eyes": "SOL",
      "Hats": "Bow",
      "Legs": "Normal",
      "Mouth": "Not Amused"
    }
  },
  "59": {
    "rank": 111,
    "attributes": {
      "Background": "Rainbow",
      "Body": "Lemon",
      "Eyes": "ETH",
      "Hats": "Horns",
      "Legs": "Normal",
      "Mouth": "Not Amused"
    }
  },
  "60": {
    "rank": 141,
    "attributes": {
      "Background": "Yellow",
      "Body": "Lime",
      "Eyes": "Sunglasses",
      "Hats": "Traffic Cone",
      "Legs": "Normal",
      "Mouth": "Not Amused"
    }
  },
  "61": {
    "rank": 10,
    "attributes": {
      "Background": "Solana",
      "Body": "Black",
      "Eyes": "Hypnotized",
      "Hats": "Flower",
      "Legs": "Normal",
      "Mouth": "Joy"
    }
  },
  "62": {
    "rank": 8,
    "attributes": {
      "Background": "Sky",
      "Body": "Black",
      "Eyes": "VR",
      "Hats": "Balloon-",
      "Legs": "Normal",
      "Mouth": "Bubblegum"
    }
  },
  "63": {
    "rank": 54,
    "attributes": {
      "Background": "Green",
      "Body": "Red",
      "Eyes": "Cyborg",
      "Hats": "Cloudy",
      "Legs": "Normal",
      "Mouth": "Shocked"
    }
  },
  "64": {
    "rank": 232,
    "attributes": {
      "Background": "Yellow",
      "Body": "Red",
      "Eyes": "Happy",
      "Hats": "Chocolate Ice Cream",
      "Legs": "Normal",
      "Mouth": "Bubblegum"
    }
  },
  "65": {
    "rank": 260,
    "attributes": {
      "Background": "Green",
      "Body": "Red",
      "Eyes": "ETH",
      "Hats": "Nothing",
      "Legs": "Normal",
      "Mouth": "Joy"
    }
  },
  "66": {
    "rank": 153,
    "attributes": {
      "Background": "Green",
      "Body": "Lemon",
      "Eyes": "Sunglasses",
      "Hats": "Cloudy",
      "Legs": "Normal",
      "Mouth": "Happy"
    }
  },
  "67": {
    "rank": 229,
    "attributes": {
      "Background": "Yellow",
      "Body": "Tatted",
      "Eyes": "Glasses",
      "Hats": "Demon Horns",
      "Legs": "Normal",
      "Mouth": "Happy"
    }
  },
  "68": {
    "rank": 290,
    "attributes": {
      "Background": "Green",
      "Body": "Tatted",
      "Eyes": "Stare",
      "Hats": "Demon Horns",
      "Legs": "Normal",
      "Mouth": "Pumpkin"
    }
  },
  "69": {
    "rank": 125,
    "attributes": {
      "Background": "Solana",
      "Body": "Black",
      "Eyes": "Hypnotized",
      "Hats": "Cloudy",
      "Legs": "Normal",
      "Mouth": "Happy"
    }
  },
  "70": {
    "rank": 115,
    "attributes": {
      "Background": "Purple",
      "Body": "Tatted",
      "Eyes": "Cyborg",
      "Hats": "Nothing",
      "Legs": "Normal",
      "Mouth": "Joy"
    }
  },
  "71": {
    "rank": 199,
    "attributes": {
      "Background": "Solana",
      "Body": "Pink Lemon",
      "Eyes": "Glasses",
      "Hats": "Thought Bubble",
      "Legs": "Normal",
      "Mouth": "Bubblegum"
    }
  },
  "72": {
    "rank": 59,
    "attributes": {
      "Background": "Rainbow",
      "Body": "Lemon",
      "Eyes": "Stars",
      "Hats": "Bow",
      "Legs": "Normal",
      "Mouth": "Bubblegum"
    }
  },
  "73": {
    "rank": 180,
    "attributes": {
      "Background": "Solana",
      "Body": "Red",
      "Eyes": "Heart",
      "Hats": "Cloudy",
      "Legs": "Normal",
      "Mouth": "Pumpkin"
    }
  },
  "74": {
    "rank": 223,
    "attributes": {
      "Background": "Purple",
      "Body": "Red",
      "Eyes": "Cute",
      "Hats": "Fire",
      "Legs": "Normal",
      "Mouth": "Happy"
    }
  },
  "75": {
    "rank": 184,
    "attributes": {
      "Background": "Yellow",
      "Body": "Black",
      "Eyes": "Stars",
      "Hats": "Signal",
      "Legs": "Normal",
      "Mouth": "Bubblegum"
    }
  },
  "76": {
    "rank": 289,
    "attributes": {
      "Background": "Rainbow",
      "Body": "Lime",
      "Eyes": "Block",
      "Hats": "Traffic Cone",
      "Legs": "Normal",
      "Mouth": "Pumpkin"
    }
  },
  "77": {
    "rank": 147,
    "attributes": {
      "Background": "Purple",
      "Body": "Tatted",
      "Eyes": "Heart",
      "Hats": "Pink Bow",
      "Legs": "Normal",
      "Mouth": "Bubblegum"
    }
  },
  "78": {
    "rank": 318,
    "attributes": {
      "Background": "Sky",
      "Body": "Tatted",
      "Eyes": "Happy",
      "Hats": "Nothing",
      "Legs": "Normal",
      "Mouth": "Shocked"
    }
  },
  "79": {
    "rank": 20,
    "attributes": {
      "Background": "Rainbow",
      "Body": "Lime",
      "Eyes": "Stars",
      "Hats": "Pink Bow",
      "Legs": "Normal",
      "Mouth": "Joy"
    }
  },
  "80": {
    "rank": 247,
    "attributes": {
      "Background": "Rainbow",
      "Body": "Lime",
      "Eyes": "Sunglasses",
      "Hats": "Nothing",
      "Legs": "Normal",
      "Mouth": "Happy"
    }
  },
  "81": {
    "rank": 327,
    "attributes": {
      "Background": "Green",
      "Body": "Lime",
      "Eyes": "Block",
      "Hats": "Thought Bubble",
      "Legs": "Normal",
      "Mouth": "Bubblegum"
    }
  },
  "82": {
    "rank": 218,
    "attributes": {
      "Background": "Purple",
      "Body": "Red",
      "Eyes": "Block",
      "Hats": "Strawberry Ice Cream",
      "Legs": "Normal",
      "Mouth": "Joy"
    }
  },
  "83": {
    "rank": 136,
    "attributes": {
      "Background": "Green",
      "Body": "Red",
      "Eyes": "Stars",
      "Hats": "Cloudy",
      "Legs": "Normal",
      "Mouth": "Not Amused"
    }
  },
  "84": {
    "rank": 208,
    "attributes": {
      "Background": "Yellow",
      "Body": "Black",
      "Eyes": "SOL",
      "Hats": "Signal",
      "Legs": "Normal",
      "Mouth": "Not Amused"
    }
  },
  "85": {
    "rank": 333,
    "attributes": {
      "Background": "Yellow",
      "Body": "Pink Lemon",
      "Eyes": "Block",
      "Hats": "Nothing",
      "Legs": "Normal",
      "Mouth": "Bubblegum"
    }
  },
  "86": {
    "rank": 78,
    "attributes": {
      "Background": "Solana",
      "Body": "Tatted",
      "Eyes": "ETH",
      "Hats": "Chocolate Ice Cream",
      "Legs": "Normal",
      "Mouth": "Joy"
    }
  },
  "87": {
    "rank": 143,
    "attributes": {
      "Background": "Rainbow",
      "Body": "Tatted",
      "Eyes": "VR",
      "Hats": "Cloudy",
      "Legs": "Normal",
      "Mouth": "Joy"
    }
  },
  "88": {
    "rank": 53,
    "attributes": {
      "Background": "Yellow",
      "Body": "Pink Lemon",
      "Eyes": "X",
      "Hats": "Fire",
      "Legs": "Normal",
      "Mouth": "Not Amused"
    }
  },
  "89": {
    "rank": 151,
    "attributes": {
      "Background": "Green",
      "Body": "Pink Lemon",
      "Eyes": "SOL",
      "Hats": "Balloon-",
      "Legs": "Normal",
      "Mouth": "Joy"
    }
  },
  "90": {
    "rank": 95,
    "attributes": {
      "Background": "Sky",
      "Body": "Lemon",
      "Eyes": "Stars",
      "Hats": "Cloudy",
      "Legs": "Normal",
      "Mouth": "Shocked"
    }
  },
  "91": {
    "rank": 323,
    "attributes": {
      "Background": "Yellow",
      "Body": "Tatted",
      "Eyes": "Block",
      "Hats": "Thought Bubble",
      "Legs": "Normal",
      "Mouth": "Not Amused"
    }
  },
  "92": {
    "rank": 121,
    "attributes": {
      "Background": "Purple",
      "Body": "Black",
      "Eyes": "Pumpkin",
      "Hats": "Horns",
      "Legs": "Normal",
      "Mouth": "Bubblegum"
    }
  },
  "93": {
    "rank": 114,
    "attributes": {
      "Background": "Yellow",
      "Body": "Lemon",
      "Eyes": "Sunglasses",
      "Hats": "Signal",
      "Legs": "Normal",
      "Mouth": "Joy"
    }
  },
  "94": {
    "rank": 179,
    "attributes": {
      "Background": "Purple",
      "Body": "Tatted",
      "Eyes": "Stars",
      "Hats": "Signal",
      "Legs": "Normal",
      "Mouth": "Not Amused"
    }
  },
  "95": {
    "rank": 130,
    "attributes": {
      "Background": "Green",
      "Body": "Lime",
      "Eyes": "Stars",
      "Hats": "Strawberry Ice Cream",
      "Legs": "Normal",
      "Mouth": "Happy"
    }
  },
  "96": {
    "rank": 128,
    "attributes": {
      "Background": "Rainbow",
      "Body": "Lemon",
      "Eyes": "SOL",
      "Hats": "Balloon-",
      "Legs": "Normal",
      "Mouth": "Bubblegum"
    }
  },
  "97": {
    "rank": 286,
    "attributes": {
      "Background": "Sky",
      "Body": "Black",
      "Eyes": "Block",
      "Hats": "Nothing",
      "Legs": "Normal",
      "Mouth": "Shocked"
    }
  },
  "98": {
    "rank": 18,
    "attributes": {
      "Background": "Purple",
      "Body": "Pink Lemon",
      "Eyes": "X",
      "Hats": "Horns",
      "Legs": "Normal",
      "Mouth": "Pumpkin"
    }
  },
  "99": {
    "rank": 72,
    "attributes": {
      "Background": "Sky",
      "Body": "Tatted",
      "Eyes": "VR",
      "Hats": "Halo",
      "Legs": "Normal",
      "Mouth": "Pumpkin"
    }
  },
  "100": {
    "rank": 301,
    "attributes": {
      "Background": "Yellow",
      "Body": "Pink Lemon",
      "Eyes": "Stare",
      "Hats": "Horns",
      "Legs": "Normal",
      "Mouth": "Pumpkin"
    }
  },
  "101": {
    "rank": 285,
    "attributes": {
      "Background": "Green",
      "Body": "Lime",
      "Eyes": "Cute",
      "Hats": "Cloudy",
      "Legs": "Normal",
      "Mouth": "Pumpkin"
    }
  },
  "102": {
    "rank": 81,
    "attributes": {
      "Background": "Green",
      "Body": "Black",
      "Eyes": "VR",
      "Hats": "Thought Bubble",
      "Legs": "Normal",
      "Mouth": "Pumpkin"
    }
  },
  "103": {
    "rank": 237,
    "attributes": {
      "Background": "Rainbow",
      "Body": "Pink Lemon",
      "Eyes": "Glasses",
      "Hats": "Thought Bubble",
      "Legs": "Normal",
      "Mouth": "Shocked"
    }
  },
  "104": {
    "rank": 113,
    "attributes": {
      "Background": "Sky",
      "Body": "Lime",
      "Eyes": "Pumpkin",
      "Hats": "Cloudy",
      "Legs": "Normal",
      "Mouth": "Not Amused"
    }
  },
  "105": {
    "rank": 158,
    "attributes": {
      "Background": "Rainbow",
      "Body": "Red",
      "Eyes": "Heart",
      "Hats": "Halo",
      "Legs": "Normal",
      "Mouth": "Joy"
    }
  },
  "106": {
    "rank": 22,
    "attributes": {
      "Background": "Green",
      "Body": "Lemon",
      "Eyes": "X",
      "Hats": "Thought Bubble",
      "Legs": "Normal",
      "Mouth": "Shocked"
    }
  },
  "107": {
    "rank": 40,
    "attributes": {
      "Background": "Yellow",
      "Body": "Tatted",
      "Eyes": "X",
      "Hats": "Signal",
      "Legs": "Normal",
      "Mouth": "Joy"
    }
  },
  "108": {
    "rank": 181,
    "attributes": {
      "Background": "Purple",
      "Body": "Lemon",
      "Eyes": "Hypnotized",
      "Hats": "Halo",
      "Legs": "Normal",
      "Mouth": "Happy"
    }
  },
  "109": {
    "rank": 132,
    "attributes": {
      "Background": "Solana",
      "Body": "Lime",
      "Eyes": "Stare",
      "Hats": "Flower",
      "Legs": "Normal",
      "Mouth": "Pumpkin"
    }
  },
  "110": {
    "rank": 317,
    "attributes": {
      "Background": "Green",
      "Body": "Pink Lemon",
      "Eyes": "Block",
      "Hats": "Thought Bubble",
      "Legs": "Normal",
      "Mouth": "Happy"
    }
  },
  "111": {
    "rank": 296,
    "attributes": {
      "Background": "Purple",
      "Body": "Tatted",
      "Eyes": "Happy",
      "Hats": "Demon Horns",
      "Legs": "Normal",
      "Mouth": "Happy"
    }
  },
  "112": {
    "rank": 312,
    "attributes": {
      "Background": "Purple",
      "Body": "Lime",
      "Eyes": "ETH",
      "Hats": "Nothing",
      "Legs": "Normal",
      "Mouth": "Pumpkin"
    }
  },
  "113": {
    "rank": 204,
    "attributes": {
      "Background": "Yellow",
      "Body": "Pink Lemon",
      "Eyes": "Heart",
      "Hats": "Balloon-",
      "Legs": "Normal",
      "Mouth": "Happy"
    }
  },
  "114": {
    "rank": 149,
    "attributes": {
      "Background": "Solana",
      "Body": "Red",
      "Eyes": "Happy",
      "Hats": "Balloon-",
      "Legs": "Normal",
      "Mouth": "Shocked"
    }
  },
  "115": {
    "rank": 145,
    "attributes": {
      "Background": "Rainbow",
      "Body": "Lemon",
      "Eyes": "VR",
      "Hats": "Nothing",
      "Legs": "Normal",
      "Mouth": "Happy"
    }
  },
  "116": {
    "rank": 222,
    "attributes": {
      "Background": "Purple",
      "Body": "Black",
      "Eyes": "SOL",
      "Hats": "Thought Bubble",
      "Legs": "Normal",
      "Mouth": "Pumpkin"
    }
  },
  "117": {
    "rank": 201,
    "attributes": {
      "Background": "Sky",
      "Body": "Pink Lemon",
      "Eyes": "Heart",
      "Hats": "Halo",
      "Legs": "Normal",
      "Mouth": "Bubblegum"
    }
  },
  "118": {
    "rank": 177,
    "attributes": {
      "Background": "Yellow",
      "Body": "Lime",
      "Eyes": "Stare",
      "Hats": "Pink Bow",
      "Legs": "Normal",
      "Mouth": "Joy"
    }
  },
  "119": {
    "rank": 227,
    "attributes": {
      "Background": "Yellow",
      "Body": "Lemon",
      "Eyes": "Happy",
      "Hats": "Balloon-",
      "Legs": "Normal",
      "Mouth": "Happy"
    }
  },
  "120": {
    "rank": 216,
    "attributes": {
      "Background": "Solana",
      "Body": "Lime",
      "Eyes": "SOL",
      "Hats": "Traffic Cone",
      "Legs": "Normal",
      "Mouth": "Shocked"
    }
  },
  "121": {
    "rank": 60,
    "attributes": {
      "Background": "Rainbow",
      "Body": "Lime",
      "Eyes": "ETH",
      "Hats": "Pink Bow",
      "Legs": "Normal",
      "Mouth": "Not Amused"
    }
  },
  "122": {
    "rank": 33,
    "attributes": {
      "Background": "Sky",
      "Body": "Lime",
      "Eyes": "Sunglasses",
      "Hats": "Strawberry Ice Cream",
      "Legs": "Normal",
      "Mouth": "Pumpkin"
    }
  },
  "123": {
    "rank": 101,
    "attributes": {
      "Background": "Sky",
      "Body": "Pink Lemon",
      "Eyes": "Block",
      "Hats": "Pink Bow",
      "Legs": "Normal",
      "Mouth": "Pumpkin"
    }
  },
  "124": {
    "rank": 273,
    "attributes": {
      "Background": "Green",
      "Body": "Pink Lemon",
      "Eyes": "Block",
      "Hats": "Chocolate Ice Cream",
      "Legs": "Normal",
      "Mouth": "Bubblegum"
    }
  },
  "125": {
    "rank": 166,
    "attributes": {
      "Background": "Purple",
      "Body": "Lime",
      "Eyes": "VR",
      "Hats": "Fire",
      "Legs": "Normal",
      "Mouth": "Pumpkin"
    }
  },
  "126": {
    "rank": 144,
    "attributes": {
      "Background": "Sky",
      "Body": "Pink Lemon",
      "Eyes": "Heart",
      "Hats": "Demon Horns",
      "Legs": "Normal",
      "Mouth": "Bubblegum"
    }
  },
  "127": {
    "rank": 197,
    "attributes": {
      "Background": "Rainbow",
      "Body": "Tatted",
      "Eyes": "Glasses",
      "Hats": "Halo",
      "Legs": "Normal",
      "Mouth": "Joy"
    }
  },
  "128": {
    "rank": 65,
    "attributes": {
      "Background": "Yellow",
      "Body": "Red",
      "Eyes": "SOL",
      "Hats": "Pink Bow",
      "Legs": "Normal",
      "Mouth": "Not Amused"
    }
  },
  "129": {
    "rank": 202,
    "attributes": {
      "Background": "Green",
      "Body": "Lime",
      "Eyes": "Heart",
      "Hats": "Bow",
      "Legs": "Normal",
      "Mouth": "Shocked"
    }
  },
  "130": {
    "rank": 209,
    "attributes": {
      "Background": "Purple",
      "Body": "Lemon",
      "Eyes": "Stare",
      "Hats": "Traffic Cone",
      "Legs": "Normal",
      "Mouth": "Not Amused"
    }
  },
  "131": {
    "rank": 16,
    "attributes": {
      "Background": "Purple",
      "Body": "Lemon",
      "Eyes": "Pumpkin",
      "Hats": "Drink",
      "Legs": "Normal",
      "Mouth": "Pumpkin"
    }
  },
  "132": {
    "rank": 206,
    "attributes": {
      "Background": "Green",
      "Body": "Red",
      "Eyes": "Glasses",
      "Hats": "Fire",
      "Legs": "Normal",
      "Mouth": "Bubblegum"
    }
  },
  "133": {
    "rank": 284,
    "attributes": {
      "Background": "Green",
      "Body": "Pink Lemon",
      "Eyes": "Stare",
      "Hats": "Strawberry Ice Cream",
      "Legs": "Normal",
      "Mouth": "Shocked"
    }
  },
  "134": {
    "rank": 154,
    "attributes": {
      "Background": "Purple",
      "Body": "Tatted",
      "Eyes": "Stars",
      "Hats": "Strawberry Ice Cream",
      "Legs": "Normal",
      "Mouth": "Happy"
    }
  },
  "135": {
    "rank": 27,
    "attributes": {
      "Background": "Solana",
      "Body": "Lime",
      "Eyes": "Sunglasses",
      "Hats": "Chocolate Ice Cream",
      "Legs": "Normal",
      "Mouth": "Pumpkin"
    }
  },
  "136": {
    "rank": 271,
    "attributes": {
      "Background": "Purple",
      "Body": "Black",
      "Eyes": "Happy",
      "Hats": "Halo",
      "Legs": "Normal",
      "Mouth": "Happy"
    }
  },
  "137": {
    "rank": 319,
    "attributes": {
      "Background": "Yellow",
      "Body": "Tatted",
      "Eyes": "ETH",
      "Hats": "Nothing",
      "Legs": "Normal",
      "Mouth": "Joy"
    }
  },
  "138": {
    "rank": 135,
    "attributes": {
      "Background": "Sky",
      "Body": "Lime",
      "Eyes": "Stare",
      "Hats": "Strawberry Ice Cream",
      "Legs": "Normal",
      "Mouth": "Not Amused"
    }
  },
  "139": {
    "rank": 131,
    "attributes": {
      "Background": "Purple",
      "Body": "Red",
      "Eyes": "Heart",
      "Hats": "Strawberry Ice Cream",
      "Legs": "Normal",
      "Mouth": "Happy"
    }
  },
  "140": {
    "rank": 331,
    "attributes": {
      "Background": "Rainbow",
      "Body": "Tatted",
      "Eyes": "Happy",
      "Hats": "Nothing",
      "Legs": "Normal",
      "Mouth": "Bubblegum"
    }
  },
  "141": {
    "rank": 94,
    "attributes": {
      "Background": "Solana",
      "Body": "Pink Lemon",
      "Eyes": "Sunglasses",
      "Hats": "Halo",
      "Legs": "Normal",
      "Mouth": "Joy"
    }
  },
  "142": {
    "rank": 13,
    "attributes": {
      "Background": "Sky",
      "Body": "Black",
      "Eyes": "VR",
      "Hats": "Demon Horns",
      "Legs": "Normal",
      "Mouth": "Bubblegum"
    }
  },
  "143": {
    "rank": 44,
    "attributes": {
      "Background": "Solana",
      "Body": "Lime",
      "Eyes": "Cute",
      "Hats": "Flower",
      "Legs": "Normal",
      "Mouth": "Joy"
    }
  },
  "144": {
    "rank": 97,
    "attributes": {
      "Background": "Rainbow",
      "Body": "Lemon",
      "Eyes": "Block",
      "Hats": "Drink",
      "Legs": "Normal",
      "Mouth": "Happy"
    }
  },
  "145": {
    "rank": 321,
    "attributes": {
      "Background": "Yellow",
      "Body": "Pink Lemon",
      "Eyes": "Happy",
      "Hats": "Cloudy",
      "Legs": "Normal",
      "Mouth": "Not Amused"
    }
  },
  "146": {
    "rank": 89,
    "attributes": {
      "Background": "Rainbow",
      "Body": "Lime",
      "Eyes": "ETH",
      "Hats": "Pink Bow",
      "Legs": "Normal",
      "Mouth": "Pumpkin"
    }
  },
  "147": {
    "rank": 269,
    "attributes": {
      "Background": "Yellow",
      "Body": "Lime",
      "Eyes": "Heart",
      "Hats": "Strawberry Ice Cream",
      "Legs": "Normal",
      "Mouth": "Shocked"
    }
  },
  "148": {
    "rank": 6,
    "attributes": {
      "Background": "Rainbow",
      "Body": "Tatted",
      "Eyes": "X",
      "Hats": "Pink Bow",
      "Legs": "Normal",
      "Mouth": "Shocked"
    }
  },
  "149": {
    "rank": 12,
    "attributes": {
      "Background": "Solana",
      "Body": "Lime",
      "Eyes": "Cyborg",
      "Hats": "Demon Horns",
      "Legs": "Normal",
      "Mouth": "Happy"
    }
  },
  "150": {
    "rank": 70,
    "attributes": {
      "Background": "Solana",
      "Body": "Lemon",
      "Eyes": "SOL",
      "Hats": "Bow",
      "Legs": "Normal",
      "Mouth": "Happy"
    }
  },
  "151": {
    "rank": 248,
    "attributes": {
      "Background": "Green",
      "Body": "Black",
      "Eyes": "ETH",
      "Hats": "Nothing",
      "Legs": "Normal",
      "Mouth": "Not Amused"
    }
  },
  "152": {
    "rank": 35,
    "attributes": {
      "Background": "Solana",
      "Body": "Tatted",
      "Eyes": "X",
      "Hats": "Fire",
      "Legs": "Normal",
      "Mouth": "Shocked"
    }
  },
  "153": {
    "rank": 170,
    "attributes": {
      "Background": "Solana",
      "Body": "Lemon",
      "Eyes": "Hypnotized",
      "Hats": "Nothing",
      "Legs": "Normal",
      "Mouth": "Not Amused"
    }
  },
  "154": {
    "rank": 167,
    "attributes": {
      "Background": "Purple",
      "Body": "Lemon",
      "Eyes": "Cute",
      "Hats": "Horns",
      "Legs": "Normal",
      "Mouth": "Pumpkin"
    }
  },
  "155": {
    "rank": 14,
    "attributes": {
      "Background": "Green",
      "Body": "Lime",
      "Eyes": "X",
      "Hats": "Horns",
      "Legs": "Normal",
      "Mouth": "Happy"
    }
  },
  "156": {
    "rank": 137,
    "attributes": {
      "Background": "Purple",
      "Body": "Tatted",
      "Eyes": "Cute",
      "Hats": "Flower",
      "Legs": "Normal",
      "Mouth": "Happy"
    }
  },
  "157": {
    "rank": 57,
    "attributes": {
      "Background": "Green",
      "Body": "Lemon",
      "Eyes": "Sunglasses",
      "Hats": "Demon Horns",
      "Legs": "Normal",
      "Mouth": "Joy"
    }
  },
  "158": {
    "rank": 17,
    "attributes": {
      "Background": "Yellow",
      "Body": "Lemon",
      "Eyes": "Cyborg",
      "Hats": "Horns",
      "Legs": "Normal",
      "Mouth": "Happy"
    }
  },
  "159": {
    "rank": 189,
    "attributes": {
      "Background": "Purple",
      "Body": "Lemon",
      "Eyes": "Cute",
      "Hats": "Halo",
      "Legs": "Normal",
      "Mouth": "Joy"
    }
  },
  "160": {
    "rank": 110,
    "attributes": {
      "Background": "Rainbow",
      "Body": "Lemon",
      "Eyes": "VR",
      "Hats": "Fire",
      "Legs": "Normal",
      "Mouth": "Bubblegum"
    }
  },
  "161": {
    "rank": 26,
    "attributes": {
      "Background": "Solana",
      "Body": "Lemon",
      "Eyes": "ETH",
      "Hats": "Flower",
      "Legs": "Normal",
      "Mouth": "Happy"
    }
  },
  "162": {
    "rank": 243,
    "attributes": {
      "Background": "Purple",
      "Body": "Pink Lemon",
      "Eyes": "ETH",
      "Hats": "Halo",
      "Legs": "Normal",
      "Mouth": "Joy"
    }
  },
  "163": {
    "rank": 287,
    "attributes": {
      "Background": "Green",
      "Body": "Tatted",
      "Eyes": "Stare",
      "Hats": "Horns",
      "Legs": "Normal",
      "Mouth": "Happy"
    }
  },
  "164": {
    "rank": 63,
    "attributes": {
      "Background": "Sky",
      "Body": "Lime",
      "Eyes": "VR",
      "Hats": "Signal",
      "Legs": "Normal",
      "Mouth": "Bubblegum"
    }
  },
  "165": {
    "rank": 122,
    "attributes": {
      "Background": "Green",
      "Body": "Black",
      "Eyes": "Pumpkin",
      "Hats": "Horns",
      "Legs": "Normal",
      "Mouth": "Bubblegum"
    }
  },
  "166": {
    "rank": 300,
    "attributes": {
      "Background": "Green",
      "Body": "Black",
      "Eyes": "Happy",
      "Hats": "Nothing",
      "Legs": "Normal",
      "Mouth": "Joy"
    }
  },
  "167": {
    "rank": 251,
    "attributes": {
      "Background": "Sky",
      "Body": "Lime",
      "Eyes": "Happy",
      "Hats": "Thought Bubble",
      "Legs": "Normal",
      "Mouth": "Pumpkin"
    }
  },
  "168": {
    "rank": 299,
    "attributes": {
      "Background": "Rainbow",
      "Body": "Lime",
      "Eyes": "Block",
      "Hats": "Halo",
      "Legs": "Normal",
      "Mouth": "Not Amused"
    }
  },
  "169": {
    "rank": 96,
    "attributes": {
      "Background": "Sky",
      "Body": "Tatted",
      "Eyes": "Stars",
      "Hats": "Signal",
      "Legs": "Normal",
      "Mouth": "Happy"
    }
  },
  "170": {
    "rank": 49,
    "attributes": {
      "Background": "Rainbow",
      "Body": "Red",
      "Eyes": "Pumpkin",
      "Hats": "Bow",
      "Legs": "Normal",
      "Mouth": "Pumpkin"
    }
  },
  "171": {
    "rank": 193,
    "attributes": {
      "Background": "Solana",
      "Body": "Lemon",
      "Eyes": "Happy",
      "Hats": "Demon Horns",
      "Legs": "Normal",
      "Mouth": "Pumpkin"
    }
  },
  "172": {
    "rank": 71,
    "attributes": {
      "Background": "Yellow",
      "Body": "Lemon",
      "Eyes": "Hypnotized",
      "Hats": "Chocolate Ice Cream",
      "Legs": "Normal",
      "Mouth": "Not Amused"
    }
  },
  "173": {
    "rank": 24,
    "attributes": {
      "Background": "Solana",
      "Body": "Black",
      "Eyes": "Cute",
      "Hats": "Flower",
      "Legs": "Normal",
      "Mouth": "Pumpkin"
    }
  },
  "174": {
    "rank": 234,
    "attributes": {
      "Background": "Yellow",
      "Body": "Black",
      "Eyes": "ETH",
      "Hats": "Halo",
      "Legs": "Normal",
      "Mouth": "Happy"
    }
  },
  "175": {
    "rank": 288,
    "attributes": {
      "Background": "Purple",
      "Body": "Tatted",
      "Eyes": "Stare",
      "Hats": "Demon Horns",
      "Legs": "Normal",
      "Mouth": "Happy"
    }
  },
  "176": {
    "rank": 326,
    "attributes": {
      "Background": "Rainbow",
      "Body": "Tatted",
      "Eyes": "Block",
      "Hats": "Halo",
      "Legs": "Normal",
      "Mouth": "Bubblegum"
    }
  },
  "177": {
    "rank": 15,
    "attributes": {
      "Background": "Rainbow",
      "Body": "Pink Lemon",
      "Eyes": "Sunglasses",
      "Hats": "Drink",
      "Legs": "Normal",
      "Mouth": "Happy"
    }
  },
  "178": {
    "rank": 196,
    "attributes": {
      "Background": "Purple",
      "Body": "Black",
      "Eyes": "Stare",
      "Hats": "Balloon-",
      "Legs": "Normal",
      "Mouth": "Shocked"
    }
  },
  "179": {
    "rank": 100,
    "attributes": {
      "Background": "Purple",
      "Body": "Lemon",
      "Eyes": "Pumpkin",
      "Hats": "Strawberry Ice Cream",
      "Legs": "Normal",
      "Mouth": "Pumpkin"
    }
  },
  "180": {
    "rank": 329,
    "attributes": {
      "Background": "Green",
      "Body": "Pink Lemon",
      "Eyes": "Block",
      "Hats": "Cloudy",
      "Legs": "Normal",
      "Mouth": "Shocked"
    }
  },
  "181": {
    "rank": 186,
    "attributes": {
      "Background": "Sky",
      "Body": "Tatted",
      "Eyes": "Heart",
      "Hats": "Cloudy",
      "Legs": "Normal",
      "Mouth": "Not Amused"
    }
  },
  "182": {
    "rank": 276,
    "attributes": {
      "Background": "Yellow",
      "Body": "Tatted",
      "Eyes": "Pumpkin",
      "Hats": "Signal",
      "Legs": "Normal",
      "Mouth": "Bubblegum"
    }
  },
  "183": {
    "rank": 69,
    "attributes": {
      "Background": "Purple",
      "Body": "Lemon",
      "Eyes": "Pumpkin",
      "Hats": "Balloon-",
      "Legs": "Normal",
      "Mouth": "Happy"
    }
  },
  "184": {
    "rank": 308,
    "attributes": {
      "Background": "Yellow",
      "Body": "Black",
      "Eyes": "Block",
      "Hats": "Fire",
      "Legs": "Normal",
      "Mouth": "Happy"
    }
  },
  "185": {
    "rank": 211,
    "attributes": {
      "Background": "Purple",
      "Body": "Lime",
      "Eyes": "Pumpkin",
      "Hats": "Demon Horns",
      "Legs": "Normal",
      "Mouth": "Shocked"
    }
  },
  "186": {
    "rank": 205,
    "attributes": {
      "Background": "Green",
      "Body": "Red",
      "Eyes": "Hypnotized",
      "Hats": "Cloudy",
      "Legs": "Normal",
      "Mouth": "Happy"
    }
  },
  "187": {
    "rank": 185,
    "attributes": {
      "Background": "Solana",
      "Body": "Lime",
      "Eyes": "Cute",
      "Hats": "Thought Bubble",
      "Legs": "Normal",
      "Mouth": "Joy"
    }
  },
  "188": {
    "rank": 325,
    "attributes": {
      "Background": "Green",
      "Body": "Tatted",
      "Eyes": "Stare",
      "Hats": "Fire",
      "Legs": "Normal",
      "Mouth": "Bubblegum"
    }
  },
  "189": {
    "rank": 277,
    "attributes": {
      "Background": "Purple",
      "Body": "Black",
      "Eyes": "SOL",
      "Hats": "Nothing",
      "Legs": "Normal",
      "Mouth": "Happy"
    }
  },
  "190": {
    "rank": 230,
    "attributes": {
      "Background": "Sky",
      "Body": "Black",
      "Eyes": "Block",
      "Hats": "Halo",
      "Legs": "Normal",
      "Mouth": "Bubblegum"
    }
  },
  "191": {
    "rank": 68,
    "attributes": {
      "Background": "Yellow",
      "Body": "Black",
      "Eyes": "Glasses",
      "Hats": "Chocolate Ice Cream",
      "Legs": "Normal",
      "Mouth": "Happy"
    }
  },
  "192": {
    "rank": 42,
    "attributes": {
      "Background": "Purple",
      "Body": "Lemon",
      "Eyes": "Glasses",
      "Hats": "Bow",
      "Legs": "Normal",
      "Mouth": "Not Amused"
    }
  },
  "193": {
    "rank": 313,
    "attributes": {
      "Background": "Rainbow",
      "Body": "Lemon",
      "Eyes": "Happy",
      "Hats": "Nothing",
      "Legs": "Normal",
      "Mouth": "Pumpkin"
    }
  },
  "194": {
    "rank": 7,
    "attributes": {
      "Background": "Yellow",
      "Body": "Pink Lemon",
      "Eyes": "Cyborg",
      "Hats": "Pink Bow",
      "Legs": "Normal",
      "Mouth": "Joy"
    }
  },
  "195": {
    "rank": 258,
    "attributes": {
      "Background": "Yellow",
      "Body": "Lime",
      "Eyes": "Hypnotized",
      "Hats": "Horns",
      "Legs": "Normal",
      "Mouth": "Shocked"
    }
  },
  "196": {
    "rank": 124,
    "attributes": {
      "Background": "Purple",
      "Body": "Red",
      "Eyes": "Happy",
      "Hats": "Chocolate Ice Cream",
      "Legs": "Normal",
      "Mouth": "Not Amused"
    }
  },
  "197": {
    "rank": 102,
    "attributes": {
      "Background": "Sky",
      "Body": "Pink Lemon",
      "Eyes": "Hypnotized",
      "Hats": "Halo",
      "Legs": "Normal",
      "Mouth": "Joy"
    }
  },
  "198": {
    "rank": 257,
    "attributes": {
      "Background": "Rainbow",
      "Body": "Lime",
      "Eyes": "Pumpkin",
      "Hats": "Nothing",
      "Legs": "Normal",
      "Mouth": "Joy"
    }
  },
  "199": {
    "rank": 173,
    "attributes": {
      "Background": "Rainbow",
      "Body": "Red",
      "Eyes": "Block",
      "Hats": "Flower",
      "Legs": "Normal",
      "Mouth": "Shocked"
    }
  },
  "200": {
    "rank": 127,
    "attributes": {
      "Background": "Solana",
      "Body": "Pink Lemon",
      "Eyes": "Cute",
      "Hats": "Traffic Cone",
      "Legs": "Normal",
      "Mouth": "Joy"
    }
  },
  "201": {
    "rank": 310,
    "attributes": {
      "Background": "Green",
      "Body": "Tatted",
      "Eyes": "Happy",
      "Hats": "Fire",
      "Legs": "Normal",
      "Mouth": "Not Amused"
    }
  },
  "202": {
    "rank": 294,
    "attributes": {
      "Background": "Rainbow",
      "Body": "Tatted",
      "Eyes": "SOL",
      "Hats": "Cloudy",
      "Legs": "Normal",
      "Mouth": "Pumpkin"
    }
  },
  "203": {
    "rank": 161,
    "attributes": {
      "Background": "Purple",
      "Body": "Lemon",
      "Eyes": "ETH",
      "Hats": "Demon Horns",
      "Legs": "Normal",
      "Mouth": "Happy"
    }
  },
  "204": {
    "rank": 275,
    "attributes": {
      "Background": "Green",
      "Body": "Lime",
      "Eyes": "ETH",
      "Hats": "Fire",
      "Legs": "Normal",
      "Mouth": "Happy"
    }
  },
  "205": {
    "rank": 61,
    "attributes": {
      "Background": "Sky",
      "Body": "Pink Lemon",
      "Eyes": "Cyborg",
      "Hats": "Nothing",
      "Legs": "Normal",
      "Mouth": "Bubblegum"
    }
  },
  "206": {
    "rank": 105,
    "attributes": {
      "Background": "Yellow",
      "Body": "Black",
      "Eyes": "Pumpkin",
      "Hats": "Horns",
      "Legs": "Normal",
      "Mouth": "Joy"
    }
  },
  "207": {
    "rank": 268,
    "attributes": {
      "Background": "Yellow",
      "Body": "Red",
      "Eyes": "SOL",
      "Hats": "Signal",
      "Legs": "Normal",
      "Mouth": "Shocked"
    }
  },
  "208": {
    "rank": 311,
    "attributes": {
      "Background": "Sky",
      "Body": "Pink Lemon",
      "Eyes": "Happy",
      "Hats": "Nothing",
      "Legs": "Normal",
      "Mouth": "Bubblegum"
    }
  },
  "209": {
    "rank": 74,
    "attributes": {
      "Background": "Solana",
      "Body": "Red",
      "Eyes": "Heart",
      "Hats": "Balloon-",
      "Legs": "Normal",
      "Mouth": "Bubblegum"
    }
  },
  "210": {
    "rank": 50,
    "attributes": {
      "Background": "Rainbow",
      "Body": "Tatted",
      "Eyes": "Stars",
      "Hats": "Drink",
      "Legs": "Normal",
      "Mouth": "Shocked"
    }
  },
  "211": {
    "rank": 292,
    "attributes": {
      "Background": "Green",
      "Body": "Pink Lemon",
      "Eyes": "Heart",
      "Hats": "Fire",
      "Legs": "Normal",
      "Mouth": "Shocked"
    }
  },
  "212": {
    "rank": 152,
    "attributes": {
      "Background": "Solana",
      "Body": "Tatted",
      "Eyes": "Cute",
      "Hats": "Balloon-",
      "Legs": "Normal",
      "Mouth": "Bubblegum"
    }
  },
  "213": {
    "rank": 213,
    "attributes": {
      "Background": "Solana",
      "Body": "Pink Lemon",
      "Eyes": "Stare",
      "Hats": "Balloon-",
      "Legs": "Normal",
      "Mouth": "Shocked"
    }
  },
  "214": {
    "rank": 307,
    "attributes": {
      "Background": "Purple",
      "Body": "Lime",
      "Eyes": "Stare",
      "Hats": "Thought Bubble",
      "Legs": "Normal",
      "Mouth": "Pumpkin"
    }
  },
  "215": {
    "rank": 253,
    "attributes": {
      "Background": "Purple",
      "Body": "Lime",
      "Eyes": "Heart",
      "Hats": "Demon Horns",
      "Legs": "Normal",
      "Mouth": "Shocked"
    }
  },
  "216": {
    "rank": 212,
    "attributes": {
      "Background": "Purple",
      "Body": "Tatted",
      "Eyes": "Glasses",
      "Hats": "Strawberry Ice Cream",
      "Legs": "Normal",
      "Mouth": "Bubblegum"
    }
  },
  "217": {
    "rank": 165,
    "attributes": {
      "Background": "Yellow",
      "Body": "Red",
      "Eyes": "Hypnotized",
      "Hats": "Horns",
      "Legs": "Normal",
      "Mouth": "Pumpkin"
    }
  },
  "218": {
    "rank": 172,
    "attributes": {
      "Background": "Purple",
      "Body": "Tatted",
      "Eyes": "Stars",
      "Hats": "Traffic Cone",
      "Legs": "Normal",
      "Mouth": "Happy"
    }
  },
  "219": {
    "rank": 108,
    "attributes": {
      "Background": "Yellow",
      "Body": "Tatted",
      "Eyes": "Pumpkin",
      "Hats": "Drink",
      "Legs": "Normal",
      "Mouth": "Bubblegum"
    }
  },
  "220": {
    "rank": 77,
    "attributes": {
      "Background": "Rainbow",
      "Body": "Lime",
      "Eyes": "Sunglasses",
      "Hats": "Strawberry Ice Cream",
      "Legs": "Normal",
      "Mouth": "Not Amused"
    }
  },
  "221": {
    "rank": 250,
    "attributes": {
      "Background": "Sky",
      "Body": "Lime",
      "Eyes": "Block",
      "Hats": "Horns",
      "Legs": "Normal",
      "Mouth": "Shocked"
    }
  },
  "222": {
    "rank": 21,
    "attributes": {
      "Background": "Solana",
      "Body": "Red",
      "Eyes": "Glasses",
      "Hats": "Bow",
      "Legs": "Normal",
      "Mouth": "Happy"
    }
  },
  "223": {
    "rank": 298,
    "attributes": {
      "Background": "Green",
      "Body": "Black",
      "Eyes": "SOL",
      "Hats": "Nothing",
      "Legs": "Normal",
      "Mouth": "Bubblegum"
    }
  },
  "224": {
    "rank": 51,
    "attributes": {
      "Background": "Yellow",
      "Body": "Lime",
      "Eyes": "Cyborg",
      "Hats": "Signal",
      "Legs": "Normal",
      "Mouth": "Not Amused"
    }
  },
  "225": {
    "rank": 249,
    "attributes": {
      "Background": "Purple",
      "Body": "Pink Lemon",
      "Eyes": "Stars",
      "Hats": "Fire",
      "Legs": "Normal",
      "Mouth": "Shocked"
    }
  },
  "226": {
    "rank": 228,
    "attributes": {
      "Background": "Purple",
      "Body": "Tatted",
      "Eyes": "Stare",
      "Hats": "Balloon-",
      "Legs": "Normal",
      "Mouth": "Joy"
    }
  },
  "227": {
    "rank": 139,
    "attributes": {
      "Background": "Solana",
      "Body": "Red",
      "Eyes": "SOL",
      "Hats": "Traffic Cone",
      "Legs": "Normal",
      "Mouth": "Bubblegum"
    }
  },
  "228": {
    "rank": 322,
    "attributes": {
      "Background": "Green",
      "Body": "Tatted",
      "Eyes": "Happy",
      "Hats": "Fire",
      "Legs": "Normal",
      "Mouth": "Pumpkin"
    }
  },
  "229": {
    "rank": 112,
    "attributes": {
      "Background": "Solana",
      "Body": "Pink Lemon",
      "Eyes": "Block",
      "Hats": "Pink Bow",
      "Legs": "Normal",
      "Mouth": "Joy"
    }
  },
  "230": {
    "rank": 58,
    "attributes": {
      "Background": "Yellow",
      "Body": "Black",
      "Eyes": "Pumpkin",
      "Hats": "Bow",
      "Legs": "Normal",
      "Mouth": "Joy"
    }
  },
  "231": {
    "rank": 98,
    "attributes": {
      "Background": "Yellow",
      "Body": "Tatted",
      "Eyes": "Cyborg",
      "Hats": "Cloudy",
      "Legs": "Normal",
      "Mouth": "Not Amused"
    }
  },
  "232": {
    "rank": 278,
    "attributes": {
      "Background": "Yellow",
      "Body": "Red",
      "Eyes": "Happy",
      "Hats": "Thought Bubble",
      "Legs": "Normal",
      "Mouth": "Joy"
    }
  },
  "233": {
    "rank": 11,
    "attributes": {
      "Background": "Rainbow",
      "Body": "Black",
      "Eyes": "Cyborg",
      "Hats": "Traffic Cone",
      "Legs": "Normal",
      "Mouth": "Bubblegum"
    }
  },
  "234": {
    "rank": 45,
    "attributes": {
      "Background": "Rainbow",
      "Body": "Red",
      "Eyes": "SOL",
      "Hats": "Drink",
      "Legs": "Normal",
      "Mouth": "Shocked"
    }
  },
  "235": {
    "rank": 120,
    "attributes": {
      "Background": "Rainbow",
      "Body": "Black",
      "Eyes": "Hypnotized",
      "Hats": "Traffic Cone",
      "Legs": "Normal",
      "Mouth": "Bubblegum"
    }
  },
  "236": {
    "rank": 256,
    "attributes": {
      "Background": "Green",
      "Body": "Red",
      "Eyes": "Stare",
      "Hats": "Traffic Cone",
      "Legs": "Normal",
      "Mouth": "Bubblegum"
    }
  },
  "237": {
    "rank": 67,
    "attributes": {
      "Background": "Green",
      "Body": "Black",
      "Eyes": "ETH",
      "Hats": "Pink Bow",
      "Legs": "Normal",
      "Mouth": "Shocked"
    }
  },
  "238": {
    "rank": 188,
    "attributes": {
      "Background": "Purple",
      "Body": "Tatted",
      "Eyes": "Hypnotized",
      "Hats": "Bow",
      "Legs": "Normal",
      "Mouth": "Bubblegum"
    }
  },
  "239": {
    "rank": 252,
    "attributes": {
      "Background": "Solana",
      "Body": "Lemon",
      "Eyes": "Stare",
      "Hats": "Thought Bubble",
      "Legs": "Normal",
      "Mouth": "Bubblegum"
    }
  },
  "240": {
    "rank": 315,
    "attributes": {
      "Background": "Green",
      "Body": "Pink Lemon",
      "Eyes": "Happy",
      "Hats": "Fire",
      "Legs": "Normal",
      "Mouth": "Happy"
    }
  },
  "241": {
    "rank": 265,
    "attributes": {
      "Background": "Purple",
      "Body": "Black",
      "Eyes": "Block",
      "Hats": "Strawberry Ice Cream",
      "Legs": "Normal",
      "Mouth": "Shocked"
    }
  },
  "242": {
    "rank": 219,
    "attributes": {
      "Background": "Yellow",
      "Body": "Tatted",
      "Eyes": "Glasses",
      "Hats": "Strawberry Ice Cream",
      "Legs": "Normal",
      "Mouth": "Pumpkin"
    }
  },
  "243": {
    "rank": 324,
    "attributes": {
      "Background": "Yellow",
      "Body": "Pink Lemon",
      "Eyes": "SOL",
      "Hats": "Nothing",
      "Legs": "Normal",
      "Mouth": "Happy"
    }
  },
  "244": {
    "rank": 241,
    "attributes": {
      "Background": "Green",
      "Body": "Lemon",
      "Eyes": "Block",
      "Hats": "Traffic Cone",
      "Legs": "Normal",
      "Mouth": "Not Amused"
    }
  },
  "245": {
    "rank": 99,
    "attributes": {
      "Background": "Solana",
      "Body": "Lemon",
      "Eyes": "Hypnotized",
      "Hats": "Horns",
      "Legs": "Normal",
      "Mouth": "Shocked"
    }
  },
  "246": {
    "rank": 254,
    "attributes": {
      "Background": "Purple",
      "Body": "Lime",
      "Eyes": "ETH",
      "Hats": "Demon Horns",
      "Legs": "Normal",
      "Mouth": "Bubblegum"
    }
  },
  "247": {
    "rank": 4,
    "attributes": {
      "Background": "Sky",
      "Body": "Black",
      "Eyes": "Glasses",
      "Hats": "Drink",
      "Legs": "Normal",
      "Mouth": "Joy"
    }
  },
  "248": {
    "rank": 73,
    "attributes": {
      "Background": "Rainbow",
      "Body": "Pink Lemon",
      "Eyes": "Cyborg",
      "Hats": "Cloudy",
      "Legs": "Normal",
      "Mouth": "Pumpkin"
    }
  },
  "249": {
    "rank": 31,
    "attributes": {
      "Background": "Purple",
      "Body": "Tatted",
      "Eyes": "Pumpkin",
      "Hats": "Drink",
      "Legs": "Normal",
      "Mouth": "Joy"
    }
  },
  "250": {
    "rank": 235,
    "attributes": {
      "Background": "Solana",
      "Body": "Black",
      "Eyes": "Happy",
      "Hats": "Signal",
      "Legs": "Normal",
      "Mouth": "Bubblegum"
    }
  },
  "251": {
    "rank": 238,
    "attributes": {
      "Background": "Green",
      "Body": "Lime",
      "Eyes": "Stare",
      "Hats": "Bow",
      "Legs": "Normal",
      "Mouth": "Happy"
    }
  },
  "252": {
    "rank": 302,
    "attributes": {
      "Background": "Solana",
      "Body": "Lime",
      "Eyes": "Stare",
      "Hats": "Nothing",
      "Legs": "Normal",
      "Mouth": "Joy"
    }
  },
  "253": {
    "rank": 314,
    "attributes": {
      "Background": "Rainbow",
      "Body": "Pink Lemon",
      "Eyes": "Cute",
      "Hats": "Nothing",
      "Legs": "Normal",
      "Mouth": "Shocked"
    }
  },
  "254": {
    "rank": 92,
    "attributes": {
      "Background": "Purple",
      "Body": "Lemon",
      "Eyes": "Stars",
      "Hats": "Demon Horns",
      "Legs": "Normal",
      "Mouth": "Happy"
    }
  },
  "255": {
    "rank": 194,
    "attributes": {
      "Background": "Solana",
      "Body": "Lemon",
      "Eyes": "Happy",
      "Hats": "Traffic Cone",
      "Legs": "Normal",
      "Mouth": "Pumpkin"
    }
  },
  "256": {
    "rank": 215,
    "attributes": {
      "Background": "Yellow",
      "Body": "Lemon",
      "Eyes": "Sunglasses",
      "Hats": "Fire",
      "Legs": "Normal",
      "Mouth": "Bubblegum"
    }
  },
  "257": {
    "rank": 200,
    "attributes": {
      "Background": "Green",
      "Body": "Pink Lemon",
      "Eyes": "Pumpkin",
      "Hats": "Halo",
      "Legs": "Normal",
      "Mouth": "Not Amused"
    }
  },
  "258": {
    "rank": 117,
    "attributes": {
      "Background": "Sky",
      "Body": "Pink Lemon",
      "Eyes": "ETH",
      "Hats": "Demon Horns",
      "Legs": "Normal",
      "Mouth": "Pumpkin"
    }
  },
  "259": {
    "rank": 262,
    "attributes": {
      "Background": "Rainbow",
      "Body": "Lemon",
      "Eyes": "SOL",
      "Hats": "Nothing",
      "Legs": "Normal",
      "Mouth": "Not Amused"
    }
  },
  "260": {
    "rank": 164,
    "attributes": {
      "Background": "Sky",
      "Body": "Tatted",
      "Eyes": "Cute",
      "Hats": "Traffic Cone",
      "Legs": "Normal",
      "Mouth": "Shocked"
    }
  },
  "261": {
    "rank": 32,
    "attributes": {
      "Background": "Sky",
      "Body": "Black",
      "Eyes": "Hypnotized",
      "Hats": "Horns",
      "Legs": "Normal",
      "Mouth": "Pumpkin"
    }
  },
  "262": {
    "rank": 84,
    "attributes": {
      "Background": "Green",
      "Body": "Tatted",
      "Eyes": "Cyborg",
      "Hats": "Fire",
      "Legs": "Normal",
      "Mouth": "Happy"
    }
  },
  "263": {
    "rank": 281,
    "attributes": {
      "Background": "Yellow",
      "Body": "Pink Lemon",
      "Eyes": "Stars",
      "Hats": "Cloudy",
      "Legs": "Normal",
      "Mouth": "Bubblegum"
    }
  },
  "264": {
    "rank": 28,
    "attributes": {
      "Background": "Rainbow",
      "Body": "Black",
      "Eyes": "VR",
      "Hats": "Horns",
      "Legs": "Normal",
      "Mouth": "Pumpkin"
    }
  },
  "265": {
    "rank": 171,
    "attributes": {
      "Background": "Purple",
      "Body": "Lime",
      "Eyes": "Glasses",
      "Hats": "Traffic Cone",
      "Legs": "Normal",
      "Mouth": "Happy"
    }
  },
  "266": {
    "rank": 280,
    "attributes": {
      "Background": "Solana",
      "Body": "Pink Lemon",
      "Eyes": "Block",
      "Hats": "Signal",
      "Legs": "Normal",
      "Mouth": "Happy"
    }
  },
  "267": {
    "rank": 66,
    "attributes": {
      "Background": "Sky",
      "Body": "Tatted",
      "Eyes": "Glasses",
      "Hats": "Traffic Cone",
      "Legs": "Normal",
      "Mouth": "Joy"
    }
  },
  "268": {
    "rank": 231,
    "attributes": {
      "Background": "Sky",
      "Body": "Black",
      "Eyes": "Block",
      "Hats": "Thought Bubble",
      "Legs": "Normal",
      "Mouth": "Shocked"
    }
  },
  "269": {
    "rank": 142,
    "attributes": {
      "Background": "Solana",
      "Body": "Lime",
      "Eyes": "Glasses",
      "Hats": "Traffic Cone",
      "Legs": "Normal",
      "Mouth": "Shocked"
    }
  },
  "270": {
    "rank": 168,
    "attributes": {
      "Background": "Purple",
      "Body": "Pink Lemon",
      "Eyes": "SOL",
      "Hats": "Flower",
      "Legs": "Normal",
      "Mouth": "Shocked"
    }
  },
  "271": {
    "rank": 246,
    "attributes": {
      "Background": "Yellow",
      "Body": "Black",
      "Eyes": "Hypnotized",
      "Hats": "Fire",
      "Legs": "Normal",
      "Mouth": "Shocked"
    }
  },
  "272": {
    "rank": 176,
    "attributes": {
      "Background": "Rainbow",
      "Body": "Pink Lemon",
      "Eyes": "ETH",
      "Hats": "Horns",
      "Legs": "Normal",
      "Mouth": "Joy"
    }
  },
  "273": {
    "rank": 174,
    "attributes": {
      "Background": "Purple",
      "Body": "Pink Lemon",
      "Eyes": "Stare",
      "Hats": "Drink",
      "Legs": "Normal",
      "Mouth": "Shocked"
    }
  },
  "274": {
    "rank": 88,
    "attributes": {
      "Background": "Sky",
      "Body": "Red",
      "Eyes": "Happy",
      "Hats": "Chocolate Ice Cream",
      "Legs": "Normal",
      "Mouth": "Shocked"
    }
  },
  "275": {
    "rank": 259,
    "attributes": {
      "Background": "Green",
      "Body": "Red",
      "Eyes": "Stare",
      "Hats": "Signal",
      "Legs": "Normal",
      "Mouth": "Happy"
    }
  },
  "276": {
    "rank": 175,
    "attributes": {
      "Background": "Sky",
      "Body": "Lemon",
      "Eyes": "Stare",
      "Hats": "Cloudy",
      "Legs": "Normal",
      "Mouth": "Joy"
    }
  },
  "277": {
    "rank": 225,
    "attributes": {
      "Background": "Purple",
      "Body": "Lime",
      "Eyes": "Block",
      "Hats": "Chocolate Ice Cream",
      "Legs": "Normal",
      "Mouth": "Not Amused"
    }
  },
  "278": {
    "rank": 207,
    "attributes": {
      "Background": "Purple",
      "Body": "Red",
      "Eyes": "Pumpkin",
      "Hats": "Fire",
      "Legs": "Normal",
      "Mouth": "Shocked"
    }
  },
  "279": {
    "rank": 183,
    "attributes": {
      "Background": "Solana",
      "Body": "Lemon",
      "Eyes": "ETH",
      "Hats": "Cloudy",
      "Legs": "Normal",
      "Mouth": "Happy"
    }
  },
  "280": {
    "rank": 263,
    "attributes": {
      "Background": "Sky",
      "Body": "Tatted",
      "Eyes": "Happy",
      "Hats": "Thought Bubble",
      "Legs": "Normal",
      "Mouth": "Happy"
    }
  },
  "281": {
    "rank": 214,
    "attributes": {
      "Background": "Rainbow",
      "Body": "Red",
      "Eyes": "SOL",
      "Hats": "Halo",
      "Legs": "Normal",
      "Mouth": "Pumpkin"
    }
  },
  "282": {
    "rank": 182,
    "attributes": {
      "Background": "Sky",
      "Body": "Lime",
      "Eyes": "Cute",
      "Hats": "Signal",
      "Legs": "Normal",
      "Mouth": "Bubblegum"
    }
  },
  "283": {
    "rank": 195,
    "attributes": {
      "Background": "Green",
      "Body": "Red",
      "Eyes": "SOL",
      "Hats": "Halo",
      "Legs": "Normal",
      "Mouth": "Joy"
    }
  },
  "284": {
    "rank": 129,
    "attributes": {
      "Background": "Solana",
      "Body": "Black",
      "Eyes": "Heart",
      "Hats": "Halo",
      "Legs": "Normal",
      "Mouth": "Happy"
    }
  },
  "285": {
    "rank": 272,
    "attributes": {
      "Background": "Yellow",
      "Body": "Lemon",
      "Eyes": "Cute",
      "Hats": "Halo",
      "Legs": "Normal",
      "Mouth": "Bubblegum"
    }
  },
  "286": {
    "rank": 25,
    "attributes": {
      "Background": "Solana",
      "Body": "Black",
      "Eyes": "Heart",
      "Hats": "Flower",
      "Legs": "Normal",
      "Mouth": "Pumpkin"
    }
  },
  "287": {
    "rank": 282,
    "attributes": {
      "Background": "Rainbow",
      "Body": "Tatted",
      "Eyes": "ETH",
      "Hats": "Halo",
      "Legs": "Normal",
      "Mouth": "Bubblegum"
    }
  },
  "288": {
    "rank": 330,
    "attributes": {
      "Background": "Green",
      "Body": "Tatted",
      "Eyes": "Happy",
      "Hats": "Nothing",
      "Legs": "Normal",
      "Mouth": "Happy"
    }
  },
  "289": {
    "rank": 155,
    "attributes": {
      "Background": "Rainbow",
      "Body": "Red",
      "Eyes": "Stare",
      "Hats": "Bow",
      "Legs": "Normal",
      "Mouth": "Pumpkin"
    }
  },
  "290": {
    "rank": 198,
    "attributes": {
      "Background": "Rainbow",
      "Body": "Tatted",
      "Eyes": "Pumpkin",
      "Hats": "Thought Bubble",
      "Legs": "Normal",
      "Mouth": "Joy"
    }
  },
  "291": {
    "rank": 264,
    "attributes": {
      "Background": "Rainbow",
      "Body": "Pink Lemon",
      "Eyes": "Glasses",
      "Hats": "Cloudy",
      "Legs": "Normal",
      "Mouth": "Shocked"
    }
  },
  "292": {
    "rank": 295,
    "attributes": {
      "Background": "Purple",
      "Body": "Tatted",
      "Eyes": "Heart",
      "Hats": "Halo",
      "Legs": "Normal",
      "Mouth": "Bubblegum"
    }
  },
  "293": {
    "rank": 191,
    "attributes": {
      "Background": "Green",
      "Body": "Red",
      "Eyes": "Cute",
      "Hats": "Demon Horns",
      "Legs": "Normal",
      "Mouth": "Bubblegum"
    }
  },
  "294": {
    "rank": 303,
    "attributes": {
      "Background": "Yellow",
      "Body": "Pink Lemon",
      "Eyes": "Sunglasses",
      "Hats": "Nothing",
      "Legs": "Normal",
      "Mouth": "Bubblegum"
    }
  },
  "295": {
    "rank": 226,
    "attributes": {
      "Background": "Green",
      "Body": "Lemon",
      "Eyes": "Block",
      "Hats": "Chocolate Ice Cream",
      "Legs": "Normal",
      "Mouth": "Bubblegum"
    }
  },
  "296": {
    "rank": 83,
    "attributes": {
      "Background": "Yellow",
      "Body": "Tatted",
      "Eyes": "VR",
      "Hats": "Chocolate Ice Cream",
      "Legs": "Normal",
      "Mouth": "Pumpkin"
    }
  },
  "297": {
    "rank": 39,
    "attributes": {
      "Background": "Rainbow",
      "Body": "Lime",
      "Eyes": "Glasses",
      "Hats": "Flower",
      "Legs": "Normal",
      "Mouth": "Joy"
    }
  },
  "298": {
    "rank": 169,
    "attributes": {
      "Background": "Green",
      "Body": "Red",
      "Eyes": "Sunglasses",
      "Hats": "Nothing",
      "Legs": "Normal",
      "Mouth": "Not Amused"
    }
  },
  "299": {
    "rank": 242,
    "attributes": {
      "Background": "Yellow",
      "Body": "Lime",
      "Eyes": "Pumpkin",
      "Hats": "Signal",
      "Legs": "Normal",
      "Mouth": "Happy"
    }
  },
  "300": {
    "rank": 116,
    "attributes": {
      "Background": "Green",
      "Body": "Lime",
      "Eyes": "SOL",
      "Hats": "Drink",
      "Legs": "Normal",
      "Mouth": "Shocked"
    }
  },
  "301": {
    "rank": 34,
    "attributes": {
      "Background": "Sky",
      "Body": "Pink Lemon",
      "Eyes": "VR",
      "Hats": "Horns",
      "Legs": "Normal",
      "Mouth": "Shocked"
    }
  },
  "302": {
    "rank": 52,
    "attributes": {
      "Background": "Purple",
      "Body": "Red",
      "Eyes": "Glasses",
      "Hats": "Flower",
      "Legs": "Normal",
      "Mouth": "Bubblegum"
    }
  },
  "303": {
    "rank": 118,
    "attributes": {
      "Background": "Rainbow",
      "Body": "Red",
      "Eyes": "Happy",
      "Hats": "Pink Bow",
      "Legs": "Normal",
      "Mouth": "Shocked"
    }
  },
  "304": {
    "rank": 306,
    "attributes": {
      "Background": "Yellow",
      "Body": "Tatted",
      "Eyes": "Cute",
      "Hats": "Fire",
      "Legs": "Normal",
      "Mouth": "Pumpkin"
    }
  },
  "305": {
    "rank": 224,
    "attributes": {
      "Background": "Solana",
      "Body": "Pink Lemon",
      "Eyes": "Block",
      "Hats": "Strawberry Ice Cream",
      "Legs": "Normal",
      "Mouth": "Joy"
    }
  },
  "306": {
    "rank": 267,
    "attributes": {
      "Background": "Yellow",
      "Body": "Black",
      "Eyes": "Happy",
      "Hats": "Signal",
      "Legs": "Normal",
      "Mouth": "Joy"
    }
  },
  "307": {
    "rank": 123,
    "attributes": {
      "Background": "Solana",
      "Body": "Pink Lemon",
      "Eyes": "SOL",
      "Hats": "Chocolate Ice Cream",
      "Legs": "Normal",
      "Mouth": "Shocked"
    }
  },
  "308": {
    "rank": 38,
    "attributes": {
      "Background": "Sky",
      "Body": "Tatted",
      "Eyes": "Stare",
      "Hats": "Drink",
      "Legs": "Normal",
      "Mouth": "Not Amused"
    }
  },
  "309": {
    "rank": 305,
    "attributes": {
      "Background": "Yellow",
      "Body": "Lemon",
      "Eyes": "Happy",
      "Hats": "Signal",
      "Legs": "Normal",
      "Mouth": "Bubblegum"
    }
  },
  "310": {
    "rank": 2,
    "attributes": {
      "Background": "Green",
      "Body": "Black",
      "Eyes": "X",
      "Hats": "Flower",
      "Legs": "Normal",
      "Mouth": "Pumpkin"
    }
  },
  "311": {
    "rank": 64,
    "attributes": {
      "Background": "Sky",
      "Body": "Tatted",
      "Eyes": "Stars",
      "Hats": "Strawberry Ice Cream",
      "Legs": "Normal",
      "Mouth": "Pumpkin"
    }
  },
  "312": {
    "rank": 91,
    "attributes": {
      "Background": "Rainbow",
      "Body": "Lime",
      "Eyes": "Hypnotized",
      "Hats": "Chocolate Ice Cream",
      "Legs": "Normal",
      "Mouth": "Happy"
    }
  },
  "313": {
    "rank": 62,
    "attributes": {
      "Background": "Purple",
      "Body": "Pink Lemon",
      "Eyes": "Cyborg",
      "Hats": "Thought Bubble",
      "Legs": "Normal",
      "Mouth": "Pumpkin"
    }
  },
  "314": {
    "rank": 157,
    "attributes": {
      "Background": "Rainbow",
      "Body": "Lime",
      "Eyes": "Happy",
      "Hats": "Flower",
      "Legs": "Normal",
      "Mouth": "Not Amused"
    }
  },
  "315": {
    "rank": 107,
    "attributes": {
      "Background": "Purple",
      "Body": "Lime",
      "Eyes": "SOL",
      "Hats": "Flower",
      "Legs": "Normal",
      "Mouth": "Not Amused"
    }
  },
  "316": {
    "rank": 41,
    "attributes": {
      "Background": "Solana",
      "Body": "Tatted",
      "Eyes": "ETH",
      "Hats": "Pink Bow",
      "Legs": "Normal",
      "Mouth": "Not Amused"
    }
  },
  "317": {
    "rank": 291,
    "attributes": {
      "Background": "Green",
      "Body": "Tatted",
      "Eyes": "Block",
      "Hats": "Traffic Cone",
      "Legs": "Normal",
      "Mouth": "Not Amused"
    }
  },
  "318": {
    "rank": 304,
    "attributes": {
      "Background": "Purple",
      "Body": "Lime",
      "Eyes": "Stare",
      "Hats": "Cloudy",
      "Legs": "Normal",
      "Mouth": "Not Amused"
    }
  },
  "319": {
    "rank": 190,
    "attributes": {
      "Background": "Rainbow",
      "Body": "Red",
      "Eyes": "Heart",
      "Hats": "Cloudy",
      "Legs": "Normal",
      "Mouth": "Not Amused"
    }
  },
  "320": {
    "rank": 163,
    "attributes": {
      "Background": "Yellow",
      "Body": "Red",
      "Eyes": "Cute",
      "Hats": "Traffic Cone",
      "Legs": "Normal",
      "Mouth": "Not Amused"
    }
  },
  "321": {
    "rank": 3,
    "attributes": {
      "Background": "Sky",
      "Body": "Tatted",
      "Eyes": "X",
      "Hats": "Chocolate Ice Cream",
      "Legs": "Normal",
      "Mouth": "Pumpkin"
    }
  },
  "322": {
    "rank": 255,
    "attributes": {
      "Background": "Rainbow",
      "Body": "Tatted",
      "Eyes": "Heart",
      "Hats": "Signal",
      "Legs": "Normal",
      "Mouth": "Happy"
    }
  },
  "323": {
    "rank": 220,
    "attributes": {
      "Background": "Yellow",
      "Body": "Black",
      "Eyes": "Hypnotized",
      "Hats": "Signal",
      "Legs": "Normal",
      "Mouth": "Bubblegum"
    }
  },
  "324": {
    "rank": 86,
    "attributes": {
      "Background": "Purple",
      "Body": "Pink Lemon",
      "Eyes": "Sunglasses",
      "Hats": "Bow",
      "Legs": "Normal",
      "Mouth": "Happy"
    }
  },
  "325": {
    "rank": 328,
    "attributes": {
      "Background": "Yellow",
      "Body": "Black",
      "Eyes": "Stare",
      "Hats": "Nothing",
      "Legs": "Normal",
      "Mouth": "Bubblegum"
    }
  },
  "326": {
    "rank": 140,
    "attributes": {
      "Background": "Solana",
      "Body": "Red",
      "Eyes": "Heart",
      "Hats": "Thought Bubble",
      "Legs": "Normal",
      "Mouth": "Happy"
    }
  },
  "327": {
    "rank": 217,
    "attributes": {
      "Background": "Rainbow",
      "Body": "Tatted",
      "Eyes": "Stars",
      "Hats": "Thought Bubble",
      "Legs": "Normal",
      "Mouth": "Pumpkin"
    }
  },
  "328": {
    "rank": 210,
    "attributes": {
      "Background": "Solana",
      "Body": "Red",
      "Eyes": "Cute",
      "Hats": "Cloudy",
      "Legs": "Normal",
      "Mouth": "Shocked"
    }
  },
  "329": {
    "rank": 309,
    "attributes": {
      "Background": "Yellow",
      "Body": "Lime",
      "Eyes": "Hypnotized",
      "Hats": "Nothing",
      "Legs": "Normal",
      "Mouth": "Happy"
    }
  },
  "330": {
    "rank": 29,
    "attributes": {
      "Background": "Purple",
      "Body": "Lemon",
      "Eyes": "VR",
      "Hats": "Bow",
      "Legs": "Normal",
      "Mouth": "Bubblegum"
    }
  },
  "331": {
    "rank": 150,
    "attributes": {
      "Background": "Yellow",
      "Body": "Lime",
      "Eyes": "VR",
      "Hats": "Thought Bubble",
      "Legs": "Normal",
      "Mouth": "Not Amused"
    }
  },
  "332": {
    "rank": 221,
    "attributes": {
      "Background": "Rainbow",
      "Body": "Pink Lemon",
      "Eyes": "Happy",
      "Hats": "Flower",
      "Legs": "Normal",
      "Mouth": "Shocked"
    }
  }
}